iautil_sql_test/__init__.py
iautil_sql_test/conn.py
iautil_sql_test/file.py
iautil_sql_test/strings.py
iautil_sql_test/version.py
iautil_sql_test-0.0.15.dist-info/LICENSE
iautil_sql_test-0.0.15.dist-info/METADATA
iautil_sql_test-0.0.15.dist-info/WHEEL
iautil_sql_test-0.0.15.dist-info/top_level.txt
iautil_sql_test-0.0.15.dist-info/RECORD
